httpSocketGateway/__init__.py
httpSocketGateway/client.py
httpSocketGateway/server.py
httpSocketGateway/utils.py
httpsocketgateway-0.3.0.1.dist-info/METADATA
httpsocketgateway-0.3.0.1.dist-info/WHEEL
httpsocketgateway-0.3.0.1.dist-info/licenses/LICENSE
httpsocketgateway-0.3.0.1.dist-info/RECORD
