Metadata-Version: 2.1
Name: httpSocketGateway
Version: 0.3.0.1
Summary: A small socket gateway server. A simple socket client for sending json
Project-URL: Homepage, https://github.com/enzom06/gateway
Project-URL: Issues, https://github.com/enzom06/gateway/issues
License-File: LICENSE
Classifier: License :: OSI Approved :: MIT License
Classifier: Operating System :: OS Independent
Classifier: Programming Language :: Python :: 3
Requires-Python: >=3.8
Requires-Dist: fastapi>=0.109.2
Requires-Dist: python-multipart>=0.0.9
Requires-Dist: requests>=2.31.0
Requires-Dist: uvicorn>=0.27.0.post1
Requires-Dist: uvicorn[standard]
Requires-Dist: websocket-client>=1.7.0
